aiovk/__init__.py
aiovk/api.py
aiovk/drivers.py
aiovk/exceptions.py
aiovk/longpoll.py
aiovk/mixins.py
aiovk/parser.py
aiovk/sessions.py
aiovk/utils.py
aiovk_varnar_fork-2.1.0.dist-info/DESCRIPTION.rst
aiovk_varnar_fork-2.1.0.dist-info/METADATA
aiovk_varnar_fork-2.1.0.dist-info/RECORD
aiovk_varnar_fork-2.1.0.dist-info/WHEEL
aiovk_varnar_fork-2.1.0.dist-info/metadata.json
aiovk_varnar_fork-2.1.0.dist-info/top_level.txt
