Metadata-Version: 2.0
Name: aiovk-varnar-fork
Version: 2.1.0
Summary: vk.com API python wrapper for asyncio
Home-page: https://github.com/Fahreeve/aiovk
Author: Fahreev Eldar
Author-email: fahreeve@yandex.ru
License: MIT License
Keywords: vk.com api vk wrappper asyncio
Platform: UNKNOWN
Classifier: Environment :: Web Environment
Classifier: Intended Audience :: Developers
Classifier: License :: OSI Approved :: MIT License
Classifier: Programming Language :: Python :: 3.5
Classifier: Programming Language :: Python :: 3.6
Classifier: Topic :: Software Development :: Libraries :: Python Modules
Requires-Dist: aiohttp (>=2.3.10)
